snatch/__init__.py
snatch/banco_central.py
snatch/base/__init__.py
snatch/base/data.py
snatch/base/data_source.py
snatch/base/schema.py
snatch/base/status.py
snatch/boa_vista.py
snatch/ceis.py
snatch/cgu_pep.py
snatch/cnep.py
snatch/config.py
snatch/data_risk.py
snatch/fgts.py
snatch/helpers/__init__.py
snatch/helpers/check_versions.py
snatch/helpers/load_fixtures.py
snatch/helpers/merge_dicts.py
snatch/helpers/only_numbers.py
snatch/helpers/secrets_manager.py
snatch/helpers/time_it.py
snatch/helpers/validator.py
snatch/ibama.py
snatch/pgfn.py
snatch/protestos.py
snatch/qsa.py
snatch/receita_federal_pj.py
snatch/serasa.py
snatch/tst.py
py_snatch-2.26.0.dist-info/WHEEL
py_snatch-2.26.0.dist-info/METADATA
py_snatch-2.26.0.dist-info/RECORD
