Metadata-Version: 2.1
Name: py-snatch
Version: 2.26.0
Summary: The Friendly Integration Library for Data Scientists. Don't You Just Know It?
Author: A55 Tech
Author-email: tech@a55.tech
Requires-Python: >=3.8,<4.0
Classifier: Programming Language :: Python :: 3
Classifier: Programming Language :: Python :: 3.10
Classifier: Programming Language :: Python :: 3.8
Classifier: Programming Language :: Python :: 3.9
Requires-Dist: Faker (>=13.11.1,<14.0.0)
Requires-Dist: arrow
Requires-Dist: asbool
Requires-Dist: boto3
Requires-Dist: jupyter (>=1.0.0,<2.0.0)
Requires-Dist: loguru
Requires-Dist: marshmallow (>=3.15.0,<4.0.0)
Requires-Dist: marshmallow-enum (>=1.5.1,<2.0.0)
Requires-Dist: pandas (>=1.4.2,<2.0.0)
Requires-Dist: python-dotenv
Requires-Dist: requests (>=2.27.1,<3.0.0)
Requires-Dist: scalpl
Requires-Dist: typing-extensions (>=4.2.0,<5.0.0)
Requires-Dist: validate-docbr
